SURE/SURE.py
SURE/__init__.py
SURE/assembly/__init__.py
SURE/assembly/assembly.py
SURE/assembly/atlas.py
SURE/codebook/__init__.py
SURE/codebook/codebook.py
SURE/utils/__init__.py
SURE/utils/custom_mlp.py
SURE/utils/queue.py
SURE/utils/utils.py
SUREv1-1.0.1.dist-info/LICENSE
SUREv1-1.0.1.dist-info/METADATA
SUREv1-1.0.1.dist-info/WHEEL
SUREv1-1.0.1.dist-info/entry_points.txt
SUREv1-1.0.1.dist-info/top_level.txt
SUREv1-1.0.1.dist-info/RECORD
