Metadata-Version: 2.1
Name: SUREv1
Version: 1.0.1
Summary: Succinct Representation of Single Cells
Home-page: https://github.com/ZengFLab/SURE
Author: Feng Zeng
Author-email: zengfeng@xmu.edu.cn
Classifier: Programming Language :: Python :: 3
Classifier: License :: OSI Approved :: MIT License
Classifier: Operating System :: OS Independent
Requires-Python: >=3.10
License-File: LICENSE
Requires-Dist: dill==0.3.8
Requires-Dist: scanpy
Requires-Dist: pytorch-ignite
Requires-Dist: datatable
Requires-Dist: scipy
Requires-Dist: numpy
Requires-Dist: scikit-learn
Requires-Dist: pandas
Requires-Dist: pyro-ppl
Requires-Dist: leidenalg
Requires-Dist: python-igraph
Requires-Dist: networkx
Requires-Dist: matplotlib
Requires-Dist: seaborn
Requires-Dist: fa2-modified
